tests
flask_moresql
