Metadata-Version: 1.1
Name: Flask-MoreSQL
Version: 0.4
Summary: Call PostgreSQL stored procedures from Flask
Home-page: http://github.com/ema/flask-moresql
Author: Emanuele Rocca
Author-email: ema@linux.it
License: BSD
Platform: any
Classifier: Development Status :: 4 - Beta
Classifier: Environment :: Web Environment
Classifier: Intended Audience :: Developers
Classifier: License :: OSI Approved :: BSD License
Classifier: Operating System :: OS Independent
Classifier: Programming Language :: Python
Classifier: Topic :: Internet :: WWW/HTTP :: Dynamic Content
Classifier: Topic :: Software Development :: Libraries :: Python Modules
